dsi/_version.py
dsi/core.py
dsi/backends/filesystem.py
dsi/backends/gufi.py
dsi/backends/parquet.py
dsi/backends/sqlite.py
dsi/plugins/collection_reader.py
dsi/plugins/env.py
dsi/plugins/file_reader.py
dsi/plugins/file_writer.py
dsi/plugins/metadata.py
dsi/plugins/plugin.py
dsi/plugins/plugin_models.py
dsi/tests/test_core.py
pydsinf-0.5.dist-info/METADATA
pydsinf-0.5.dist-info/WHEEL
pydsinf-0.5.dist-info/top_level.txt
pydsinf-0.5.dist-info/RECORD
