Metadata-Version: 2.1
Name: pydsinf
Version: 0.5
Summary: A Data Science Infrastructure Metadatabase
Author-email: Jesus Pulido <pulido@lanl.gov>, James Ahrens <ahrens@lanl.gov>, Divya Banesh <dbanesh@lanl.gov>, Hugh Greenberg <hng@lanl.gov>, Ben Sims <bsims@lanl.gov>, Christine Sweeney <cahrens@lanl.gov>, Terry Turton <tlturton@lanl.gov>, Quincy Wofford <qwofford@lanl.gov>
License: BSD-3-Clause
Classifier: Programming Language :: Python
Requires-Dist: pandas >=2.0.2
Requires-Dist: pyarrow >=12.0.1
Requires-Dist: pydantic >=2.1.1
Requires-Dist: nbconvert >=7.13.0
Requires-Dist: gitpython >=3.0.0
